{
	"native": "Lëtzebuergesch",
	"english": "Luxembourgish",
	"wikipedia": "https://en.wikipedia.org/wiki/Luxembourgish",
	"direction": "ltr",
	"langcode-1": "lb",
	"langcode-2": "ltz",
	"langcode-3": "ltz",
	"translated-names": [
		{ "langcode": "af", "translation": "Luxemburgs" },
		{ "langcode": "sq", "translation": "Luksemburgase" },
		{ "langcode": "am", "translation": "ሉክዜምብርጊሽ" },
		{ "langcode": "ar", "translation": "اللوكسمبرجية" },
		{ "langcode": "hy", "translation": "Լյուքսեմբուրգերեն" },
		{ "langcode": "az", "translation": "Lüksemburq" },
		{ "langcode": "eu", "translation": "Luxenburgera" },
		{ "langcode": "bn", "translation": "লুক্সেমবার্গীয়" },
		{ "langcode": "my", "translation": "လူဇင်ဘတ်" },
		{ "langcode": "bs", "translation": "Luksemburški" },
		{ "langcode": "bg", "translation": "Люксембургски" },
		{ "langcode": "ny", "translation": "Wachi Luxembourg" },
		{ "langcode": "zh", "translation": "卢森堡语" },
		{ "langcode": "da", "translation": "Luxembourgsk" },
		{ "langcode": "de", "translation": "Luxemburgisch" },
		{ "langcode": "en", "translation": "Luxembourgish" },
		{ "langcode": "eo", "translation": "Luksemburga" },
		{ "langcode": "et", "translation": "Luksemburgi" },
		{ "langcode": "fi", "translation": "Luxemburgilainen" },
		{ "langcode": "fr", "translation": "Luxembourgeois" },
		{ "langcode": "gl", "translation": "Luxemburgués" },
		{ "langcode": "ka", "translation": "ლუქსემბურგული" },
		{ "langcode": "el", "translation": "Λουξεμβούργο" },
		{ "langcode": "gu", "translation": "લક્ઝમબર્ગિશ" },
		{ "langcode": "ht", "translation": "Luxembourgish" },
		{ "langcode": "ha", "translation": "Harshen Luxembourgish" },
		{ "langcode": "he", "translation": "לוקסמבורגית" },
		{ "langcode": "hi", "translation": "लक्जमबर्गिश" },
		{ "langcode": "ig", "translation": "Asụsụ Luxembourgish" },
		{ "langcode": "id", "translation": "Luksemburg" },
		{ "langcode": "ga", "translation": "Lucsamburg" },
		{ "langcode": "is", "translation": "Lúxemborgískt" },
		{ "langcode": "it", "translation": "Lussemburghese" },
		{ "langcode": "ja", "translation": "ルクセンブルク語" },
		{ "langcode": "jv", "translation": "Luksemburg" },
		{ "langcode": "yi", "translation": "לוקסעמבורגיש" },
		{ "langcode": "kn", "translation": "ಲಕ್ಸೆಂಬರ್ಗ್" },
		{ "langcode": "kk", "translation": "Люксембургтік" },
		{ "langcode": "ca", "translation": "Luxemburguès" },
		{ "langcode": "km", "translation": "លុចសំបួរ" },
		{ "langcode": "rw", "translation": "Luxembourgish" },
		{ "langcode": "ky", "translation": "Люксембургча" },
		{ "langcode": "ko", "translation": "룩셈부르크 어" },
		{ "langcode": "co", "translation": "Lussemburghese" },
		{ "langcode": "hr", "translation": "Luksemburški" },
		{ "langcode": "ku", "translation": "Luksembûrgî" },
		{ "langcode": "lo", "translation": "ພາສາລາວ" },
		{ "langcode": "lv", "translation": "Luksemburgiešu" },
		{ "langcode": "lt", "translation": "Liuksemburgiečių" },
		{ "langcode": "lb", "translation": "Lëtzebuergesch" },
		{ "langcode": "mg", "translation": "Luxembourgish" },
		{ "langcode": "ml", "translation": "ലക്സംബർഗ്" },
		{ "langcode": "mt", "translation": "Lussemburgiż" },
		{ "langcode": "mi", "translation": "Luxembourgish" },
		{ "langcode": "mr", "translation": "लक्झेंबर्गिश" },
		{ "langcode": "mk", "translation": "Луксембуршки" },
		{ "langcode": "mn", "translation": "Люксембург" },
		{ "langcode": "ne", "translation": "लक्जमबर्गिश" },
		{ "langcode": "nl", "translation": "Luxemburgs" },
		{ "langcode": "no", "translation": "Luxemburgisk" },
		{ "langcode": "or", "translation": "ଲକ୍ସେମବର୍ଗ" },
		{ "langcode": "ps", "translation": "لوګزامبورګي" },
		{ "langcode": "fa", "translation": "لوکزامبورگی" },
		{ "langcode": "pl", "translation": "Luksemburski" },
		{ "langcode": "pt", "translation": "Luxemburguês" },
		{ "langcode": "pa", "translation": "ਲਕਸਮਬਰਗੀ" },
		{ "langcode": "ro", "translation": "Luxemburgheză" },
		{ "langcode": "ru", "translation": "Люксембургский" },
		{ "langcode": "sm", "translation": "Lusemipoukisi" },
		{ "langcode": "gd", "translation": "Luxembourgach" },
		{ "langcode": "sv", "translation": "Luxemburgiska" },
		{ "langcode": "sr", "translation": "Луксембуршки" },
		{ "langcode": "st", "translation": "Se-Luxembourg" },
		{ "langcode": "sn", "translation": "Rukusembogi" },
		{ "langcode": "sd", "translation": "لڪسمبرگي" },
		{ "langcode": "si", "translation": "ලක්සම්බර්ග්" },
		{ "langcode": "sk", "translation": "Luxemburčina" },
		{ "langcode": "sl", "translation": "Luksemburški" },
		{ "langcode": "so", "translation": "Luxembourgish" },
		{ "langcode": "es", "translation": "Luxemburgués" },
		{ "langcode": "sw", "translation": "Kilasembagi" },
		{ "langcode": "tg", "translation": "Люксембургӣ" },
		{ "langcode": "ta", "translation": "லக்சம்பர்க்" },
		{ "langcode": "tt", "translation": "Люксембург" },
		{ "langcode": "te", "translation": "లక్సెంబర్గ్" },
		{ "langcode": "th", "translation": "ลักเซมเบิร์ก" },
		{ "langcode": "cs", "translation": "Lucemburština" },
		{ "langcode": "tr", "translation": "Lüksemburgca" },
		{ "langcode": "tk", "translation": "Lýuksemburg" },
		{ "langcode": "ug", "translation": "لىيۇكسېمبۇرگ" },
		{ "langcode": "uk", "translation": "Люксембурзький" },
		{ "langcode": "hu", "translation": "Luxemburgi" },
		{ "langcode": "ur", "translation": "لکسمبرگ" },
		{ "langcode": "uz", "translation": "Lyuksemburg" },
		{ "langcode": "vi", "translation": "Tiếng Luxembourg" },
		{ "langcode": "cy", "translation": "Lwcsembwrg" },
		{ "langcode": "be", "translation": "Люксембургскі" },
		{ "langcode": "xh", "translation": "isiLuksembogu" },
		{ "langcode": "yo", "translation": "Ede Luxembourgish" },
		{ "langcode": "zu", "translation": "Isi-Luxembourgish" }
	]
}
